[
    {
        "title": "The English Patient",
        "author": "Michael Ondaantje",
        "status": "Read",
        "isbn": "385529"
    },
    {
        "title": "Eye of God",
        "author": "James Rollins",
        "status": "Read",
        "isbn": "1000"
    },
    {
        "title": "The English Patient",
        "author": "Michael Ondaantje",
        "status": "Read",
        "isbn": "2000"
    },
    {
        "title": "Deep Fathom",
        "author": "James Rollins",
        "status": "Read",
        "isbn": "3000"
    },
    {
        "title": "Humiliated and Insulted",
        "author": "Fyodor Dostoevsky",
        "status": "Read",
        "isbn": "4000"
    },
    {
        "title": "How to make friends and influence people",
        "author": "Dale Carnegie",
        "status": "In progress",
        "isbn": "6000"
    },
    {
        "title": "Introspection",
        "author": "Marcus Aurelius",
        "status": "In progress",
        "isbn": "8000"
    },
    {
        "title": "1984",
        "author": "George Orwell",
        "status": "Not read",
        "isbn": "9000"
    },
    {
        "title": "Recunoaste-ma",
        "author": "Adrian Olariu",
        "status": "Not Published",
        "isbn": "10000"
    },
    {
        "title": "Error",
        "author": "Error",
        "status": "Error",
        "isbn": "123"
    }
]